README.md
setup.py
HusBot/TeleBusiness.py
HusBot.egg-info/PKG-INFO
HusBot.egg-info/SOURCES.txt
HusBot.egg-info/dependency_links.txt
HusBot.egg-info/requires.txt
HusBot.egg-info/top_level.txt